charlie/__init__.py
charlie/utils.py
charlie/feature_selection/__init__.py
charlie/feature_selection/rfecv.py
charlie/models/__init__.py
charlie/models/clustering.py
charlie/models/cross_validation.py
charlie/models/ensemble.py
charliepy-2.0.6.dist-info/licenses/LICENSE
charliepy-2.0.6.dist-info/METADATA
charliepy-2.0.6.dist-info/WHEEL
charliepy-2.0.6.dist-info/top_level.txt
charliepy-2.0.6.dist-info/RECORD
