Metadata-Version: 2.4
Name: charliepy
Version: 2.0.6
Summary: Ensemble Machine Learning Algorithm to rival XGBoost and RandomForest
Home-page: https://github.com/StatsGary/charlie
Author: Gary Hutson
Author-email: hutsons-hacks@outlook.com
Classifier: Programming Language :: Python :: 3.9
Classifier: Programming Language :: Python :: 3.10
Classifier: Programming Language :: Python :: 3.11
Classifier: Programming Language :: Python :: 3.12
Classifier: License :: OSI Approved :: MIT License
Classifier: Operating System :: OS Independent
Requires-Python: >=3.9
License-File: LICENSE
Requires-Dist: torch
Requires-Dist: scikit-learn
Requires-Dist: tqdm
Provides-Extra: dev
Requires-Dist: pytest>=7.0; extra == "dev"
Dynamic: author
Dynamic: author-email
Dynamic: classifier
Dynamic: description
Dynamic: description-content-type
Dynamic: home-page
Dynamic: license-file
Dynamic: provides-extra
Dynamic: requires-dist
Dynamic: requires-python
Dynamic: summary
